{
  "nodes": [
    {
      "id": "t0",
      "label": "Oʻahu agricola, windward e central plain",
      "layer": 0,
      "status": "documentato"
    },
    {
      "id": "t1",
      "label": "Altre isole hawaiane e piantagioni",
      "layer": 0,
      "status": "documentato"
    },
    {
      "id": "t2",
      "label": "Pacifico, costa occidentale statunitense e Asia",
      "layer": 0,
      "status": "documentato"
    },
    {
      "id": "t3",
      "label": "Honolulu Harbor, aeroporto e rete stradale",
      "layer": 0,
      "status": "documentato"
    },
    {
      "id": "r0",
      "label": "Taro, ortaggi, frutta tropicale e uova",
      "layer": 1,
      "status": "documentato"
    },
    {
      "id": "r1",
      "label": "Zucchero, ananas, carne e caffè",
      "layer": 1,
      "status": "documentato"
    },
    {
      "id": "r2",
      "label": "Riso, pesce, conserve e prodotti refrigerati",
      "layer": 1,
      "status": "documentato"
    },
    {
      "id": "r3",
      "label": "Alimenti per residenti, militari e turismo",
      "layer": 1,
      "status": "documentato"
    },
    {
      "id": "a0",
      "label": "Mercati, cooperative e piccoli coltivatori",
      "layer": 2,
      "status": "documentato"
    },
    {
      "id": "a1",
      "label": "Piantagioni, camion, navi interinsulari e grossisti",
      "layer": 2,
      "status": "documentato"
    },
    {
      "id": "a2",
      "label": "Pescatori, importatori e basi militari",
      "layer": 2,
      "status": "documentato"
    },
    {
      "id": "a3",
      "label": "Supermercati, hotels, ristoranti e food service",
      "layer": 2,
      "status": "documentato"
    },
    {
      "id": "x0",
      "label": "Refrigerazione, inscatolamento e lavorazione dell’ananas",
      "layer": 3,
      "status": "documentato"
    },
    {
      "id": "x1",
      "label": "Macinazione dello zucchero, macellazione e panificazione",
      "layer": 3,
      "status": "documentato"
    },
    {
      "id": "x2",
      "label": "Preparazioni Native Hawaiian, giapponesi, cinesi e filippine",
      "layer": 3,
      "status": "documentato"
    },
    {
      "id": "x3",
      "label": "Catering alberghiero, mense militari e ristorazione turistica",
      "layer": 3,
      "status": "documentato"
    },
    {
      "id": "p0",
      "label": "Poi, pesce, riso e frutta",
      "layer": 4,
      "status": "documentato"
    },
    {
      "id": "p1",
      "label": "Carne, pane, conserve e latticini",
      "layer": 4,
      "status": "documentato"
    },
    {
      "id": "p2",
      "label": "Plate lunch e cucine locali multietniche",
      "layer": 4,
      "status": "documentato"
    },
    {
      "id": "p3",
      "label": "Consumi diseguali fra Waikīkī, basi, sobborghi e comunità native",
      "layer": 4,
      "status": "documentato"
    }
  ],
  "edges": [
    {
      "source": "t0",
      "target": "r0",
      "status": "documentato",
      "label": "relazione funzionale attestata o ricostruita"
    },
    {
      "source": "t0",
      "target": "r2",
      "status": "sintesi",
      "label": "relazione funzionale attestata o ricostruita"
    },
    {
      "source": "t1",
      "target": "r1",
      "status": "documentato",
      "label": "relazione funzionale attestata o ricostruita"
    },
    {
      "source": "t1",
      "target": "r3",
      "status": "sintesi",
      "label": "relazione funzionale attestata o ricostruita"
    },
    {
      "source": "t2",
      "target": "r2",
      "status": "documentato",
      "label": "relazione funzionale attestata o ricostruita"
    },
    {
      "source": "t2",
      "target": "r0",
      "status": "sintesi",
      "label": "relazione funzionale attestata o ricostruita"
    },
    {
      "source": "t3",
      "target": "r3",
      "status": "documentato",
      "label": "relazione funzionale attestata o ricostruita"
    },
    {
      "source": "t3",
      "target": "r1",
      "status": "sintesi",
      "label": "relazione funzionale attestata o ricostruita"
    },
    {
      "source": "r0",
      "target": "a0",
      "status": "documentato",
      "label": "relazione funzionale attestata o ricostruita"
    },
    {
      "source": "r0",
      "target": "a3",
      "status": "sintesi",
      "label": "relazione funzionale attestata o ricostruita"
    },
    {
      "source": "r1",
      "target": "a1",
      "status": "documentato",
      "label": "relazione funzionale attestata o ricostruita"
    },
    {
      "source": "r1",
      "target": "a3",
      "status": "sintesi",
      "label": "relazione funzionale attestata o ricostruita"
    },
    {
      "source": "r2",
      "target": "a2",
      "status": "documentato",
      "label": "relazione funzionale attestata o ricostruita"
    },
    {
      "source": "r2",
      "target": "a0",
      "status": "sintesi",
      "label": "relazione funzionale attestata o ricostruita"
    },
    {
      "source": "r3",
      "target": "a3",
      "status": "documentato",
      "label": "relazione funzionale attestata o ricostruita"
    },
    {
      "source": "r3",
      "target": "a2",
      "status": "sintesi",
      "label": "relazione funzionale attestata o ricostruita"
    },
    {
      "source": "a0",
      "target": "x0",
      "status": "documentato",
      "label": "relazione funzionale attestata o ricostruita"
    },
    {
      "source": "a0",
      "target": "x2",
      "status": "documentato",
      "label": "relazione funzionale attestata o ricostruita"
    },
    {
      "source": "a1",
      "target": "x1",
      "status": "documentato",
      "label": "relazione funzionale attestata o ricostruita"
    },
    {
      "source": "a1",
      "target": "x0",
      "status": "sintesi",
      "label": "relazione funzionale attestata o ricostruita"
    },
    {
      "source": "a2",
      "target": "x2",
      "status": "documentato",
      "label": "relazione funzionale attestata o ricostruita"
    },
    {
      "source": "a2",
      "target": "x3",
      "status": "sintesi",
      "label": "relazione funzionale attestata o ricostruita"
    },
    {
      "source": "a3",
      "target": "x3",
      "status": "documentato",
      "label": "relazione funzionale attestata o ricostruita"
    },
    {
      "source": "a3",
      "target": "x1",
      "status": "sintesi",
      "label": "relazione funzionale attestata o ricostruita"
    },
    {
      "source": "x0",
      "target": "p0",
      "status": "documentato",
      "label": "relazione funzionale attestata o ricostruita"
    },
    {
      "source": "x0",
      "target": "p3",
      "status": "sintesi",
      "label": "relazione funzionale attestata o ricostruita"
    },
    {
      "source": "x1",
      "target": "p1",
      "status": "documentato",
      "label": "relazione funzionale attestata o ricostruita"
    },
    {
      "source": "x1",
      "target": "p3",
      "status": "sintesi",
      "label": "relazione funzionale attestata o ricostruita"
    },
    {
      "source": "x2",
      "target": "p2",
      "status": "documentato",
      "label": "relazione funzionale attestata o ricostruita"
    },
    {
      "source": "x2",
      "target": "p0",
      "status": "sintesi",
      "label": "relazione funzionale attestata o ricostruita"
    },
    {
      "source": "x3",
      "target": "p3",
      "status": "documentato",
      "label": "relazione funzionale attestata o ricostruita"
    },
    {
      "source": "x3",
      "target": "p2",
      "status": "sintesi",
      "label": "relazione funzionale attestata o ricostruita"
    }
  ]
}
