{
  "nodes": [
    {
      "id": "t0",
      "label": "Piantagioni del Tidewater e Chesapeake",
      "layer": 0,
      "status": "documentato"
    },
    {
      "id": "t1",
      "label": "Fiumi James e York, paludi e costa",
      "layer": 0,
      "status": "documentato"
    },
    {
      "id": "t2",
      "label": "Orti, pascoli e mercati cittadini",
      "layer": 0,
      "status": "documentato"
    },
    {
      "id": "t3",
      "label": "Atlantico, Caraibi e reti coloniali",
      "layer": 0,
      "status": "documentato"
    },
    {
      "id": "r0",
      "label": "Mais, grano, legumi e patate dolci",
      "layer": 1,
      "status": "documentato"
    },
    {
      "id": "r1",
      "label": "Pesce, ostriche, granchi e sale",
      "layer": 1,
      "status": "documentato"
    },
    {
      "id": "r2",
      "label": "Carne, latte, pollame, frutta e ortaggi",
      "layer": 1,
      "status": "documentato"
    },
    {
      "id": "r3",
      "label": "Zucchero, melassa, tè, vino e spezie",
      "layer": 1,
      "status": "documentato"
    },
    {
      "id": "a0",
      "label": "Agricoltura di piantagione e mercato",
      "layer": 2,
      "status": "documentato"
    },
    {
      "id": "a1",
      "label": "Pesca, navigazione fluviale e raccolta",
      "layer": 2,
      "status": "documentato"
    },
    {
      "id": "a2",
      "label": "Orticoltura, allevamento e servizio domestico",
      "layer": 2,
      "status": "documentato"
    },
    {
      "id": "a3",
      "label": "Dogane, trasporto e commercio atlantico",
      "layer": 2,
      "status": "documentato"
    },
    {
      "id": "x0",
      "label": "Molitura, panificazione e bollitura",
      "layer": 3,
      "status": "documentato"
    },
    {
      "id": "x1",
      "label": "Salatura, affumicatura e conserve",
      "layer": 3,
      "status": "documentato"
    },
    {
      "id": "x2",
      "label": "Macellazione, caseificazione e sidro",
      "layer": 3,
      "status": "documentato"
    },
    {
      "id": "x3",
      "label": "Taverne, cucine, mercati e dispense istituzionali",
      "layer": 3,
      "status": "documentato"
    },
    {
      "id": "p0",
      "label": "Pane, mais, legumi e tuberi",
      "layer": 4,
      "status": "documentato"
    },
    {
      "id": "p1",
      "label": "Pesce, ostriche e prodotti salati",
      "layer": 4,
      "status": "documentato"
    },
    {
      "id": "p2",
      "label": "Carni, latticini, frutta e ortaggi",
      "layer": 4,
      "status": "documentato"
    },
    {
      "id": "p3",
      "label": "Consumo di élite e razioni imposte agli schiavi",
      "layer": 4,
      "status": "documentato"
    }
  ],
  "edges": [
    {
      "source": "t0",
      "target": "r0",
      "status": "documentato",
      "label": "relazione funzionale attestata o ricostruita"
    },
    {
      "source": "t0",
      "target": "r2",
      "status": "sintesi",
      "label": "relazione funzionale attestata o ricostruita"
    },
    {
      "source": "t1",
      "target": "r1",
      "status": "documentato",
      "label": "relazione funzionale attestata o ricostruita"
    },
    {
      "source": "t1",
      "target": "r3",
      "status": "sintesi",
      "label": "relazione funzionale attestata o ricostruita"
    },
    {
      "source": "t2",
      "target": "r2",
      "status": "documentato",
      "label": "relazione funzionale attestata o ricostruita"
    },
    {
      "source": "t2",
      "target": "r0",
      "status": "sintesi",
      "label": "relazione funzionale attestata o ricostruita"
    },
    {
      "source": "t3",
      "target": "r3",
      "status": "documentato",
      "label": "relazione funzionale attestata o ricostruita"
    },
    {
      "source": "t3",
      "target": "r1",
      "status": "sintesi",
      "label": "relazione funzionale attestata o ricostruita"
    },
    {
      "source": "r0",
      "target": "a0",
      "status": "documentato",
      "label": "relazione funzionale attestata o ricostruita"
    },
    {
      "source": "r0",
      "target": "a3",
      "status": "sintesi",
      "label": "relazione funzionale attestata o ricostruita"
    },
    {
      "source": "r1",
      "target": "a1",
      "status": "documentato",
      "label": "relazione funzionale attestata o ricostruita"
    },
    {
      "source": "r1",
      "target": "a3",
      "status": "sintesi",
      "label": "relazione funzionale attestata o ricostruita"
    },
    {
      "source": "r2",
      "target": "a2",
      "status": "documentato",
      "label": "relazione funzionale attestata o ricostruita"
    },
    {
      "source": "r2",
      "target": "a0",
      "status": "sintesi",
      "label": "relazione funzionale attestata o ricostruita"
    },
    {
      "source": "r3",
      "target": "a3",
      "status": "documentato",
      "label": "relazione funzionale attestata o ricostruita"
    },
    {
      "source": "r3",
      "target": "a2",
      "status": "sintesi",
      "label": "relazione funzionale attestata o ricostruita"
    },
    {
      "source": "a0",
      "target": "x0",
      "status": "documentato",
      "label": "relazione funzionale attestata o ricostruita"
    },
    {
      "source": "a0",
      "target": "x2",
      "status": "documentato",
      "label": "relazione funzionale attestata o ricostruita"
    },
    {
      "source": "a1",
      "target": "x1",
      "status": "documentato",
      "label": "relazione funzionale attestata o ricostruita"
    },
    {
      "source": "a1",
      "target": "x0",
      "status": "sintesi",
      "label": "relazione funzionale attestata o ricostruita"
    },
    {
      "source": "a2",
      "target": "x2",
      "status": "documentato",
      "label": "relazione funzionale attestata o ricostruita"
    },
    {
      "source": "a2",
      "target": "x3",
      "status": "sintesi",
      "label": "relazione funzionale attestata o ricostruita"
    },
    {
      "source": "a3",
      "target": "x3",
      "status": "documentato",
      "label": "relazione funzionale attestata o ricostruita"
    },
    {
      "source": "a3",
      "target": "x1",
      "status": "sintesi",
      "label": "relazione funzionale attestata o ricostruita"
    },
    {
      "source": "x0",
      "target": "p0",
      "status": "documentato",
      "label": "relazione funzionale attestata o ricostruita"
    },
    {
      "source": "x0",
      "target": "p3",
      "status": "sintesi",
      "label": "relazione funzionale attestata o ricostruita"
    },
    {
      "source": "x1",
      "target": "p1",
      "status": "documentato",
      "label": "relazione funzionale attestata o ricostruita"
    },
    {
      "source": "x1",
      "target": "p3",
      "status": "sintesi",
      "label": "relazione funzionale attestata o ricostruita"
    },
    {
      "source": "x2",
      "target": "p2",
      "status": "documentato",
      "label": "relazione funzionale attestata o ricostruita"
    },
    {
      "source": "x2",
      "target": "p0",
      "status": "sintesi",
      "label": "relazione funzionale attestata o ricostruita"
    },
    {
      "source": "x3",
      "target": "p3",
      "status": "documentato",
      "label": "relazione funzionale attestata o ricostruita"
    },
    {
      "source": "x3",
      "target": "p2",
      "status": "sintesi",
      "label": "relazione funzionale attestata o ricostruita"
    }
  ]
}
